asktheapi_team_builder/__init__.py
asktheapi_team_builder/types.py
asktheapi_team_builder/core/__init__.py
asktheapi_team_builder/core/agent_builder.py
asktheapi_team_builder/core/api_spec_handler.py
asktheapi_team_builder/core/http_client.py
asktheapi_team_builder/core/models.py
asktheapi_team_builder/core/team_builder.py
asktheapi_team_builder/core/tool_builder.py
asktheapi_team_builder/prompts/__init__.py
asktheapi_team_builder/prompts/agents_apispec_prompt.py
asktheapi_team_builder/prompts/evaluate_agents_prompt.py
asktheapi_team_builder/prompts/run_agents_prompt.py
asktheapi_team_builder/services/__init__.py
asktheapi_team_builder/services/agent_evaluator_service.py
asktheapi_team_builder/services/llm_service.py
asktheapi_team_builder/services/mcp_service.py
asktheapi_team_builder/services/open_ai_service.py
asktheapi_team_builder-0.3.2.dist-info/licenses/LICENSE
asktheapi_team_builder-0.3.2.dist-info/METADATA
asktheapi_team_builder-0.3.2.dist-info/WHEEL
asktheapi_team_builder-0.3.2.dist-info/top_level.txt
asktheapi_team_builder-0.3.2.dist-info/RECORD
