Metadata-Version: 2.4
Name: asktheapi-team-builder
Version: 0.3.2
Summary: A high-level library for building and managing teams of AutoGen agents
Author: Alex Albala
Project-URL: Homepage, https://github.com/alexalbala/asktheapi-team-builder
Project-URL: Bug Tracker, https://github.com/alexalbala/asktheapi-team-builder/issues
Project-URL: Documentation, https://github.com/alexalbala/asktheapi-team-builder#readme
Project-URL: Source Code, https://github.com/alexalbala/asktheapi-team-builder
Keywords: autogen,agents,ai,team,automation,llm,openai,openapi
Classifier: Development Status :: 3 - Alpha
Classifier: Intended Audience :: Developers
Classifier: License :: OSI Approved :: MIT License
Classifier: Operating System :: OS Independent
Classifier: Programming Language :: Python :: 3
Classifier: Programming Language :: Python :: 3.8
Classifier: Programming Language :: Python :: 3.9
Classifier: Programming Language :: Python :: 3.10
Classifier: Programming Language :: Python :: 3.11
Classifier: Topic :: Software Development :: Libraries :: Python Modules
Classifier: Topic :: Scientific/Engineering :: Artificial Intelligence
Requires-Python: >=3.8
License-File: LICENSE
Requires-Dist: autogen-agentchat>=0.4.7
Requires-Dist: autogen-ext[openai]>=0.4.7
Requires-Dist: aiohttp>=3.8.0
Requires-Dist: pydantic>=2.0.0
Requires-Dist: openai>=1.63.2
Requires-Dist: pyyaml>=6.0.0
Requires-Dist: fastmcp>=0.4.1
Provides-Extra: dev
Requires-Dist: pytest>=7.0.0; extra == "dev"
Requires-Dist: pytest-asyncio>=0.21.0; extra == "dev"
Requires-Dist: pytest-cov>=4.1.0; extra == "dev"
Requires-Dist: black>=23.0.0; extra == "dev"
Requires-Dist: isort>=5.12.0; extra == "dev"
Requires-Dist: flake8>=6.1.0; extra == "dev"
Requires-Dist: mypy>=1.5.0; extra == "dev"
Requires-Dist: sphinx>=7.0.0; extra == "dev"
Requires-Dist: sphinx-rtd-theme>=1.3.0; extra == "dev"
Dynamic: license-file
